pyspark_transform_registry/__init__.py
pyspark_transform_registry/core.py
pyspark_transform_registry/helpers.py
pyspark_transform_registry/model_wrapper.py
pyspark_transform_registry-0.12.0.dist-info/METADATA
pyspark_transform_registry-0.12.0.dist-info/WHEEL
pyspark_transform_registry-0.12.0.dist-info/top_level.txt
pyspark_transform_registry-0.12.0.dist-info/RECORD
