Metadata-Version: 2.4
Name: pyspark-transform-registry
Version: 0.12.0
Summary: A PySpark transform registry with MLflow integration.
Requires-Python: >=3.9
Requires-Dist: mlflow>=3.0.0
